{
  "version": 1,
  "functions": {
    "/api/admin/assinaturas/redefinir-senha": {},
    "/api/admin/daws/criar": {},
    "/api/admin/daws/editar-arquivos": {},
    "/api/admin/drum-kit/criar": {},
    "/api/admin/drum-kit/editar-arquivos": {},
    "/api/admin/plugins/criar": {},
    "/api/admin/plugins/editar-arquivos": {},
    "/api/admin/programas/criar": {},
    "/api/admin/programas/editar-arquivos": {},
    "/api/daws": {},
    "/api/download-gratis/baixar": {},
    "/api/download-gratis/iniciar": {},
    "/api/download-gratis/status": {},
    "/api/drum-kit": {},
    "/api/plugins": {},
    "/api/programas": {}
  }
}